{
    "NSFW": "UNLIKELY",
    "similarity": 0.3241439163684845,
    "LICENSE": "?",
    "SAMPLE_ID": 1830649012325.0,
    "caption": "Promotional Jerzees Nublend Full-Zip Hooded Sweatshirt",
    "url": "http://images.theexecutiveadvertising.com/productimages/manf/jet/products/993MR-C.jpg",
    "key": "000000051",
    "status": "success",
    "error_message": null,
    "width": 400,
    "height": 400,
    "original_width": 400,
    "original_height": 400,
    "exif": "{}",
    "sha256": "82d27a940e5fde706019aa3e744f35b6a23853399342b563c255c45ff92ecb37"
}