{
    "NSFW": "UNSURE",
    "similarity": 0.3327813446521759,
    "LICENSE": "?",
    "SAMPLE_ID": 3444496007295.0,
    "caption": "Little Big Town - I'm With The Band",
    "url": "https://media3.woopic.com/api/v1/images/156%2Fv%2FOg6901Tyf6EvF99-n%2Flittle-big-town-i-m-with-the-band%7Cx240?format=300x175&facedetect=1&quality=85",
    "key": "000002372",
    "status": "success",
    "error_message": null,
    "width": 300,
    "height": 175,
    "original_width": 300,
    "original_height": 175,
    "exif": "{}",
    "sha256": "760a0809e9aa052dcd64b4cce5221cd059d8a0e597e70f46fce0b55086990a31"
}