{
    "NSFW": "UNLIKELY",
    "similarity": 0.33123335242271423,
    "LICENSE": "?",
    "SAMPLE_ID": 4195443015969.0,
    "caption": "Sue Lindstrom on site of the new MUSC Children's Hospital.",
    "url": "http://chswomeninbusiness.com/wp-content/uploads/2019/05/sue-lindstrom-musc.jpg",
    "key": "000005787",
    "status": "success",
    "error_message": null,
    "width": 1000,
    "height": 602,
    "original_width": 1000,
    "original_height": 602,
    "exif": "{}",
    "sha256": "a1f8de56ce9c6c9a8b8935ddd268d1598262a21d7677d5c49fb9f720c51ad890"
}