{
    "NSFW": "UNLIKELY",
    "similarity": 0.32082271575927734,
    "LICENSE": "?",
    "SAMPLE_ID": 1596004017597.0,
    "caption": "little girl with decorative onion flowers photo",
    "url": "https://us.123rf.com/450wm/taikuri/taikuri0811/taikuri081100049/4339350-little-girl-with-decorative-onion-flowers.jpg",
    "key": "000008033",
    "status": "success",
    "error_message": null,
    "width": 450,
    "height": 300,
    "original_width": 450,
    "original_height": 300,
    "exif": "{}",
    "sha256": "7acadf081fd128193b6e94b9f5a2276d2379c1cd6e54751059a051b40d7669f2"
}