{
    "NSFW": "UNLIKELY",
    "similarity": 0.3011035919189453,
    "LICENSE": "?",
    "SAMPLE_ID": 3072285009092.0,
    "caption": "The Witcher 3 : Wild Hunt Complete Edition - Comparatif graphique et informations techniques",
    "url": "http://images.niooz.fr/safe_image.php?width=332&i=/cache/mediaid/3/1/4/7/2/1/31472144.jpg",
    "key": "000005197",
    "status": "success",
    "error_message": null,
    "width": 332,
    "height": 142,
    "original_width": 332,
    "original_height": 142,
    "exif": "{}",
    "sha256": "c11195596474777bab7f39d7da66cdb997815e29a90bf89e558948ed11d074ce"
}