{
    "NSFW": "UNLIKELY",
    "similarity": 0.31740596890449524,
    "LICENSE": "?",
    "SAMPLE_ID": 3453439033464.0,
    "caption": "\"\"\"Cold Pursuit\"\" - Liam Neeson\"",
    "url": "https://kinosztukwalki.pl/wp-content/uploads/2019/01/coldpursuitliamneeson.png",
    "key": "000001273",
    "status": "success",
    "error_message": null,
    "width": 750,
    "height": 250,
    "original_width": 750,
    "original_height": 250,
    "exif": "{}",
    "sha256": "7b18d8b6b64efa2f818a46ad9d5c47f5afbf04b838fa01300d47427a663749d0"
}