{
    "NSFW": "UNLIKELY",
    "similarity": 0.31746625900268555,
    "LICENSE": "?",
    "SAMPLE_ID": 2816180000945.0,
    "caption": "Creative make-up new conceptual idea. blue red yellow white bold body art painting. Crazy new graphic abstract picture on woman face surrealistic. Horizontal professional photo. Creativity background Stockfoto",
    "url": "https://us.123rf.com/450wm/olgaosa/olgaosa1711/olgaosa171100795/90021285-creative-make-up-new-conceptual-idea-blue-red-yellow-white-bold-body-art-painting-crazy-new-graphic-.jpg?ver=6",
    "key": "000005658",
    "status": "success",
    "error_message": null,
    "width": 450,
    "height": 300,
    "original_width": 450,
    "original_height": 300,
    "exif": "{}",
    "sha256": "94d985098ac532c3b63f95d633b3e76451c32b8c63106b6518a1d4695fdf79d1"
}