{
    "NSFW": "UNLIKELY",
    "similarity": 0.3071497678756714,
    "LICENSE": "?",
    "SAMPLE_ID": 3706052007173.0,
    "caption": "intro-tournament",
    "url": "https://getfishing.com.au/wp-content/uploads/2018/05/intro-tournament.jpg",
    "key": "000004483",
    "status": "success",
    "error_message": null,
    "width": 220,
    "height": 165,
    "original_width": 220,
    "original_height": 165,
    "exif": "{}",
    "sha256": "5d95f31ec63856f76c184d5c0cb7e9755c5340ce3b13254a7b877279aa82eaa0"
}