{
    "NSFW": "UNLIKELY",
    "similarity": 0.34545862674713135,
    "LICENSE": "?",
    "SAMPLE_ID": 12145029773.0,
    "caption": "Hellraiser Halloween Shot - photo copyright Cheri Loughlin - The Intoxicologist",
    "url": "https://intoxicologist.net/wp-content/uploads/2010/10/Hellraiser-Halloween-Shot-photo-copyright-Cheri-Loughlin-The-Intoxicologist-240x300.jpg",
    "key": "000006045",
    "status": "success",
    "error_message": null,
    "width": 240,
    "height": 300,
    "original_width": 240,
    "original_height": 300,
    "exif": "{}",
    "sha256": "d4f535fe3141d1bffbddcb000c2d4985e87af00cc720779e79fea0a3c2c0a458"
}