{
    "NSFW": "UNLIKELY",
    "similarity": 0.3666333854198456,
    "LICENSE": "?",
    "SAMPLE_ID": 2426596009563.0,
    "caption": "Lara Ramage was once the 'face of Surf Life Saving Queensland', she also greeted tourists at Coolangatta airport with water safety leaflets. Photo: Geoff McLachlan",
    "url": "https://media.apnarm.net.au/media/images/2018/01/06/imagev111d3386811392992d2ae8a8b8534e027-q6js57404jq9fsbvjp2_t460.jpg",
    "key": "000005646",
    "status": "success",
    "error_message": null,
    "width": 650,
    "height": 1000,
    "original_width": 650,
    "original_height": 1000,
    "exif": "{}",
    "sha256": "c5af3a32edfe03ccb36717d5331572a5a99e2ad6b878dcb082e16b6593f759e3"
}